agent/__init__.py
agent/a.py
agent/device.py
agent/exceptions.py
agent_py-0.0.24.dist-info/LICENSE.md
agent_py-0.0.24.dist-info/METADATA
agent_py-0.0.24.dist-info/WHEEL
agent_py-0.0.24.dist-info/top_level.txt
agent_py-0.0.24.dist-info/RECORD
