Metadata-Version: 2.1
Name: agent-py
Version: 0.0.24
Summary: A python wrapper around the Agent REST API.
Home-page: https://github.com/ispysoftware/agent-py
Author: Sean Tearney
Author-email: sean@ispyconnect.com
License: Apache Software License
Platform: any
Classifier: Intended Audience :: Developers
Classifier: License :: OSI Approved :: Apache Software License
Classifier: Operating System :: OS Independent
Classifier: Programming Language :: Python
Classifier: Programming Language :: Python :: 3
Classifier: Topic :: Software Development :: Libraries :: Python Modules
